volt_logger-0.1.0.dist-info/licenses/LICENSE
voltlogger/__init__.py
voltlogger/logger.py
volt_logger-0.1.0.dist-info/METADATA
volt_logger-0.1.0.dist-info/WHEEL
volt_logger-0.1.0.dist-info/top_level.txt
volt_logger-0.1.0.dist-info/RECORD
