Metadata-Version: 2.4
Name: volt-logger
Version: 0.1.0
Summary: A lightweight logger for Python CLI tools and scripts
Home-page: https://github.com/stuarttempleton/volt-logger
Author: Voltur
License: MIT License
Project-URL: Homepage, https://github.com/stuarttempleton/volt-logger
Project-URL: Repository, https://github.com/stuarttempleton/volt-logger
Project-URL: Bug Tracker, https://github.com/stuarttempleton/volt-logger/issues
Keywords: logging,structured,volt
Classifier: Programming Language :: Python :: 3
Classifier: License :: OSI Approved :: MIT License
Classifier: Operating System :: OS Independent
Requires-Python: >=3.7
License-File: LICENSE
Provides-Extra: test
Requires-Dist: pytest; extra == "test"
Dynamic: author
Dynamic: home-page
Dynamic: license-file
Dynamic: requires-python
